<?xml version="1.0" encoding="utf-8" ?>
<dwsync>
<file name="bootstrap-theme.css" server="dentalrealestate.co" local="130367714820000000" remote="130401459000000000" Dst="-1" />
<file name="bootstrap-theme.min.css" server="dentalrealestate.co" local="130367714820000000" remote="130401459000000000" Dst="-1" />
<file name="bootstrap-theme.css.map" server="dentalrealestate.co" local="130367714820000000" remote="130401459000000000" Dst="-1" />
<file name="bootstrap.css" server="dentalrealestate.co" local="130367714820000000" remote="130401459000000000" Dst="-1" />
<file name="bootstrap.min.css" server="dentalrealestate.co" local="130367714820000000" remote="130401459000000000" Dst="-1" />
<file name="bootstrap.css.map" server="dentalrealestate.co" local="130367714820000000" remote="130401459000000000" Dst="-1" />
<file name="bootstrap-theme.css" server="myfiremedia.net" local="3478553880" remote="2093027984470869272" Dst="-1" />
<file name="bootstrap-theme.css.map" server="myfiremedia.net" local="3478553880" remote="2095818510622426392" Dst="-1" />
<file name="bootstrap-theme.min.css" server="myfiremedia.net" local="3478553880" remote="2093027348815709464" Dst="-1" />
<file name="bootstrap.css" server="myfiremedia.net" local="3478553880" remote="2093844612372661528" Dst="-1" />
<file name="bootstrap.css.map" server="myfiremedia.net" local="3478553940" remote="2093844612372661588" Dst="-1" />
<file name="bootstrap.min.css" server="myfiremedia.net" local="3478553880" remote="2093845248027821336" Dst="-1" />
<file name="bootstrap-theme.css" server="ftp.myfiremedia.net" local="130401826800000000" remote="130769014200000000" Dst="2" />
<file name="bootstrap-theme.css.map" server="ftp.myfiremedia.net" local="130401826800000000" remote="130769014200000000" Dst="2" />
<file name="bootstrap-theme.min.css" server="ftp.myfiremedia.net" local="130401826800000000" remote="130769014200000000" Dst="2" />
<file name="bootstrap.css" server="ftp.myfiremedia.net" local="130401826800000000" remote="130769014200000000" Dst="2" />
<file name="bootstrap.css.map" server="ftp.myfiremedia.net" local="130401827400000000" remote="130769014200000000" Dst="2" />
<file name="bootstrap.min.css" server="ftp.myfiremedia.net" local="130401826800000000" remote="130769014200000000" Dst="2" />
</dwsync>